{
	"configurations" : 
	[
		{
			"directories" : 
			[
				{
					"build" : ".",
					"jsonFile" : "directory-.-Debug-d0094a50bb2071803777.json",
					"minimumCMakeVersion" : 
					{
						"string" : "3.30"
					},
					"projectIndex" : 0,
					"source" : ".",
					"targetIndexes" : 
					[
						0
					]
				}
			],
			"name" : "Debug",
			"projects" : 
			[
				{
					"directoryIndexes" : 
					[
						0
					],
					"name" : "ex02_Dia_da_Semana",
					"targetIndexes" : 
					[
						0
					]
				}
			],
			"targets" : 
			[
				{
					"directoryIndex" : 0,
					"id" : "ex02_Dia_da_Semana::@6890427a1f51a3e7e1df",
					"jsonFile" : "target-ex02_Dia_da_Semana-Debug-efb2aed11401222129c9.json",
					"name" : "ex02_Dia_da_Semana",
					"projectIndex" : 0
				}
			]
		}
	],
	"kind" : "codemodel",
	"paths" : 
	{
		"build" : "C:/Users/user/segundo_semestre_fatec/linguagem_de_programacao/if_else/ex02_Dia da Semana/cmake-build-debug",
		"source" : "C:/Users/user/segundo_semestre_fatec/linguagem_de_programacao/if_else/ex02_Dia da Semana"
	},
	"version" : 
	{
		"major" : 2,
		"minor" : 7
	}
}
