{
	"configurations" : 
	[
		{
			"directories" : 
			[
				{
					"build" : ".",
					"jsonFile" : "directory-.-Debug-d0094a50bb2071803777.json",
					"minimumCMakeVersion" : 
					{
						"string" : "3.30"
					},
					"projectIndex" : 0,
					"source" : ".",
					"targetIndexes" : 
					[
						0
					]
				}
			],
			"name" : "Debug",
			"projects" : 
			[
				{
					"directoryIndexes" : 
					[
						0
					],
					"name" : "ex01_descontos",
					"targetIndexes" : 
					[
						0
					]
				}
			],
			"targets" : 
			[
				{
					"directoryIndex" : 0,
					"id" : "ex01_descontos::@6890427a1f51a3e7e1df",
					"jsonFile" : "target-ex01_descontos-Debug-c6ac5300337fb8833245.json",
					"name" : "ex01_descontos",
					"projectIndex" : 0
				}
			]
		}
	],
	"kind" : "codemodel",
	"paths" : 
	{
		"build" : "C:/Users/user/segundo_semestre_fatec/linguagem_de_programacao/if_else/ex01_descontos/cmake-build-debug",
		"source" : "C:/Users/user/segundo_semestre_fatec/linguagem_de_programacao/if_else/ex01_descontos"
	},
	"version" : 
	{
		"major" : 2,
		"minor" : 7
	}
}
